azure/cognitiveservices/search/visualsearch/__init__.py
azure/cognitiveservices/search/visualsearch/version.py
azure/cognitiveservices/search/visualsearch/visual_search_client.py
azure/cognitiveservices/search/visualsearch/models/__init__.py
azure/cognitiveservices/search/visualsearch/models/action.py
azure/cognitiveservices/search/visualsearch/models/action_py3.py
azure/cognitiveservices/search/visualsearch/models/aggregate_offer.py
azure/cognitiveservices/search/visualsearch/models/aggregate_offer_py3.py
azure/cognitiveservices/search/visualsearch/models/aggregate_rating.py
azure/cognitiveservices/search/visualsearch/models/aggregate_rating_py3.py
azure/cognitiveservices/search/visualsearch/models/creative_work.py
azure/cognitiveservices/search/visualsearch/models/creative_work_py3.py
azure/cognitiveservices/search/visualsearch/models/crop_area.py
azure/cognitiveservices/search/visualsearch/models/crop_area_py3.py
azure/cognitiveservices/search/visualsearch/models/error.py
azure/cognitiveservices/search/visualsearch/models/error_py3.py
azure/cognitiveservices/search/visualsearch/models/error_response.py
azure/cognitiveservices/search/visualsearch/models/error_response_py3.py
azure/cognitiveservices/search/visualsearch/models/filters.py
azure/cognitiveservices/search/visualsearch/models/filters_py3.py
azure/cognitiveservices/search/visualsearch/models/identifiable.py
azure/cognitiveservices/search/visualsearch/models/identifiable_py3.py
azure/cognitiveservices/search/visualsearch/models/image_action.py
azure/cognitiveservices/search/visualsearch/models/image_action_py3.py
azure/cognitiveservices/search/visualsearch/models/image_entity_action.py
azure/cognitiveservices/search/visualsearch/models/image_entity_action_py3.py
azure/cognitiveservices/search/visualsearch/models/image_info.py
azure/cognitiveservices/search/visualsearch/models/image_info_py3.py
azure/cognitiveservices/search/visualsearch/models/image_knowledge.py
azure_cognitiveservices_search_visualsearch-0.2.0.dist-info/METADATA
azure_cognitiveservices_search_visualsearch-0.2.0.dist-info/WHEEL
azure_cognitiveservices_search_visualsearch-0.2.0.dist-info/top_level.txt
azure_cognitiveservices_search_visualsearch-0.2.0.dist-info/RECORD
